RequestMap/EndpointMap.py
RequestMap/Exceptions.py
RequestMap/__init__.py
RequestMap/Protocols/Flask.py
RequestMap/Protocols/ProtocolBase.py
RequestMap/Protocols/__init__.py
RequestMap/Response/JSON.py
RequestMap/Response/ResponseBase.py
RequestMap/Response/__init__.py
RequestMap/Utilities/JITDictionary.py
RequestMap/Utilities/__init__.py
RequestMap/Validators/ValidatorBase.py
RequestMap/Validators/__init__.py
RequestMap-1.0.3.dist-info/LICENSE
RequestMap-1.0.3.dist-info/METADATA
RequestMap-1.0.3.dist-info/WHEEL
RequestMap-1.0.3.dist-info/top_level.txt
RequestMap-1.0.3.dist-info/RECORD
