Metadata-Version: 2.1
Name: RequestMap
Version: 1.0.3
Summary: RequestMap is a micro framework for API developments.
Home-page: https://github.com/yyjlincoln/RequestMap
Author: Yijun Yan
Author-email: yyjlincoln@gmail.com
License: Apache
Platform: UNKNOWN
Classifier: License :: OSI Approved :: Apache Software License
Classifier: Programming Language :: Python :: 3
Classifier: Programming Language :: Python :: 3.7
License-File: LICENSE
Requires-Dist: flask
